hyperspace_explorer/__init__.py
hyperspace_explorer/configurables.py
hyperspace_explorer/hyperspace_worker.py
hyperspace_explorer/queue.py
hyperspace_explorer/results.py
hyperspace_explorer/scenario_base.py
hyperspace_explorer/utils.py
hyperspace_explorer-0.3.1.data/scripts/hyperspace_worker.py
hyperspace_explorer-0.3.1.dist-info/LICENSE
hyperspace_explorer-0.3.1.dist-info/METADATA
hyperspace_explorer-0.3.1.dist-info/WHEEL
hyperspace_explorer-0.3.1.dist-info/top_level.txt
hyperspace_explorer-0.3.1.dist-info/RECORD
