Metadata-Version: 2.1
Name: hyperspace-explorer
Version: 0.3.1
Summary: Tracking, queueing and distributed execution of ML/DL experiments. Helping define and semi-automatically explore hyper-parameter spaces.
Home-page: https://github.com/tpietruszka/hyperspace_explorer
Author: Tomasz Pietruszka
Author-email: tomek.pietruszka@gmail.com
License: UNKNOWN
Platform: UNKNOWN
Requires-Python: >=3.7
Requires-Dist: sacred (>=0.8.1)
Requires-Dist: pymongo (>=3.9.0)
Provides-Extra: analysis
Requires-Dist: pandas (>=1.0.1) ; extra == 'analysis'
Provides-Extra: dev
Requires-Dist: commitizen (>=1.16.4) ; extra == 'dev'
Requires-Dist: pytest ; extra == 'dev'
